LICENSE
README.md
setup.py
serverlesspack/__init__.py
serverlesspack/cli.py
serverlesspack/cli_cache.py
serverlesspack/configuration_client.py
serverlesspack/exceptions.py
serverlesspack/imports_resolver.py
serverlesspack/packager.py
serverlesspack/packages_lock_client.py
serverlesspack/process_node_handlers.py
serverlesspack/progress.py
serverlesspack/spinner.py
serverlesspack/utils.py
serverlesspack.egg-info/PKG-INFO
serverlesspack.egg-info/SOURCES.txt
serverlesspack.egg-info/dependency_links.txt
serverlesspack.egg-info/entry_points.txt
serverlesspack.egg-info/requires.txt
serverlesspack.egg-info/top_level.txt